.gitignore
LICENSE.txt
MANIFEST.in
Makefile
README.md
imports_check.py
requirements.txt
setup.py
.github/workflows/regression.yml
.github/workflows/regression_no_munittest.yml
.github/workflows/stale.yml
omas/__init__.py
omas/omas_ascii.py
omas/omas_cocos.py
omas/omas_core.py
omas/omas_cython.pyx
omas/omas_ds.py
omas/omas_h5.py
omas/omas_hdc.py
omas/omas_imas.py
omas/omas_json.py
omas/omas_machine.py
omas/omas_mongo.py
omas/omas_nc.py
omas/omas_physics.py
omas/omas_plot.py
omas/omas_s3.py
omas/omas_sample.py
omas/omas_setup.py
omas/omas_structure.py
omas/omas_symbols.py
omas/omas_uda.py
omas/omas_utils.py
omas/version
omas.egg-info/PKG-INFO
omas.egg-info/SOURCES.txt
omas.egg-info/dependency_links.txt
omas.egg-info/requires.txt
omas.egg-info/top_level.txt
omas/examples/README.txt
omas/examples/__init__.py
omas/examples/across_ODSs.py
omas/examples/connect_gkdb.py
omas/examples/consistency_check.py
omas/examples/extra_structures.py
omas/examples/geqdsk_to_from_imas.py
omas/examples/iter_scenario.py
omas/examples/ods_process_input_data.py
omas/examples/ods_sample.py
omas/examples/omas_cocos.py
omas/examples/omas_collection.py
omas/examples/omas_coordinates.py
omas/examples/omas_dynamic_imas.py
omas/examples/omas_dynamic_machine.py
omas/examples/omas_dynamic_nc.py
omas/examples/omas_info.py
omas/examples/omas_mongo_example.py
omas/examples/omas_resample.py
omas/examples/omas_time.py
omas/examples/omas_uda_example.py
omas/examples/omas_units.py
omas/examples/parse_codeparameters.py
omas/examples/plot_g_s_2_ip.py
omas/examples/plot_omas.py
omas/examples/plot_omas_omfit.py
omas/examples/plot_omas_overlays.py
omas/examples/plot_quantity.py
omas/examples/plot_saveload_scaling.py
omas/examples/save_load_all.py
omas/examples/save_load_through.py
omas/examples/showcase_paths.py
omas/examples/simple_imas.py
omas/examples/solps_imas.py
omas/examples/uncertain.py
omas/examples/west_geqdsk.py
omas/examples/west_imas.py
omas/imas_structures/3_10_0/_coordinates.json
omas/imas_structures/3_10_0/_global_quantities.json
omas/imas_structures/3_10_0/_times.json
omas/imas_structures/3_10_0/actuator.json
