Metadata-Version: 2.1
Name: omas
Version: 0.94.2
Summary: Ordered Multidimensional Array Structures
Home-page: https://gafusion.github.io/omas
Author: Orso Meneghini
License: MIT
Keywords: integrated modeling OMFIT IMAS ITER
Classifier: License :: OSI Approved :: MIT License
Classifier: Programming Language :: Python :: 3
Provides-Extra: machine
Provides-Extra: hdc
Provides-Extra: imas
Provides-Extra: uda
Provides-Extra: mongo
Provides-Extra: s3
Provides-Extra: build_structures
Provides-Extra: build_documentation
License-File: LICENSE.txt
